bebanjo
