Metadata-Version: 2.1
Name: bebanjo-api-hi2meuk
Version: 1.3.0
Summary: A client library for interacting with Bebanjo's Movida and Seqeuence APIs.
Home-page: https://gitlab.com/hi2meuk/bebanjo-api
Author: Steve Beaumont
Author-email: steve@hi2.me.uk
License: UNKNOWN
Platform: UNKNOWN
Classifier: Programming Language :: Python :: 3
Classifier: License :: OSI Approved :: MIT License
Classifier: Operating System :: OS Independent
Classifier: Intended Audience :: Developers
Requires-Python: >=3
